llama_index/VERSION
llama_index/__init__.py
llama_index/async_utils.py
llama_index/constants.py
llama_index/img_utils.py
llama_index/py.typed
llama_index/schema.py
llama_index/types.py
llama_index/utils.py
llama_index/agent/__init__.py
llama_index/agent/context_retriever_agent.py
llama_index/agent/openai_agent.py
llama_index/agent/retriever_openai_agent.py
llama_index/agent/types.py
llama_index/agent/react/__init__.py
llama_index/agent/react/base.py
llama_index/agent/react/formatter.py
llama_index/agent/react/output_parser.py
llama_index/agent/react/prompts.py
llama_index/agent/react/types.py
llama_index/bridge/__init__.py
llama_index/bridge/langchain.py
llama_index/bridge/pydantic.py
llama_index/callbacks/__init__.py
llama_index/callbacks/aim.py
llama_index/callbacks/arize_phoenix_callback.py
llama_index/callbacks/base.py
llama_index/callbacks/base_handler.py
llama_index/callbacks/finetuning_handler.py
llama_index/callbacks/global_handlers.py
llama_index/callbacks/llama_debug.py
llama_index/callbacks/open_inference_callback.py
llama_index/callbacks/schema.py
llama_index/callbacks/simple_llm_handler.py
llama_index/callbacks/token_counting.py
llama_index/callbacks/utils.py
llama_index/callbacks/wandb_callback.py
llama_index/chat_engine/__init__.py
llama_index/chat_engine/condense_question.py
llama_index/chat_engine/context.py
llama_index/chat_engine/simple.py
llama_index/chat_engine/types.py
llama_index/chat_engine/utils.py
llama_index/composability/__init__.py
llama_index/composability/base.py
llama_index/composability/joint_qa_summary.py
llama_index/data_structs/__init__.py
llama_index/data_structs/data_structs.py
llama_index/data_structs/document_summary.py
llama_index/data_structs/registry.py
llama_index/data_structs/struct_type.py
llama_index/data_structs/table.py
llama_index/embeddings/__init__.py
llama_index/embeddings/adapter.py
llama_index/embeddings/adapter_utils.py
llama_index/embeddings/base.py
llama_index/embeddings/clarifai.py
gpt_index-0.8.42.dist-info/LICENSE
gpt_index-0.8.42.dist-info/METADATA
gpt_index-0.8.42.dist-info/WHEEL
gpt_index-0.8.42.dist-info/top_level.txt
gpt_index-0.8.42.dist-info/RECORD
