Metadata-Version: 2.1
Name: gpt_index
Version: 0.8.42
Summary: Interface between LLMs and your data
Home-page: https://github.com/jerryjliu/llama_index
Author: Jerry Liu
License: MIT
License-File: LICENSE
Requires-Dist: tiktoken
Requires-Dist: dataclasses_json
Requires-Dist: langchain>=0.0.303
Requires-Dist: sqlalchemy>=2.0.15
Requires-Dist: numpy
Requires-Dist: tenacity<9.0.0,>=8.2.0
Requires-Dist: openai>=0.26.4
Requires-Dist: pandas
Requires-Dist: urllib3<2
Requires-Dist: fsspec>=2023.5.0
Requires-Dist: typing-inspect>=0.8.0
Requires-Dist: typing_extensions>=4.5.0
Requires-Dist: beautifulsoup4
Requires-Dist: nest_asyncio
Requires-Dist: nltk
